twisstool/__init__.py
twisstool-1.20.dist-info/METADATA
twisstool-1.20.dist-info/WHEEL
twisstool-1.20.dist-info/top_level.txt
twisstool-1.20.dist-info/RECORD
