Metadata-Version: 2.1
Name: twisstool
Version: 1.20
Summary: tool for loading any MADX table files like twiss tables etc..
Home-page: https://gitlab.cern.ch/ttydecks/twisstool
Author: ttydecks / CERN BE-OP-LHC
Author-email: tobias.tydecks@cern.ch
License: UNKNOWN
Platform: UNKNOWN
Classifier: Programming Language :: Python :: 3
Classifier: Operating System :: OS Independent
